neverbounce_sdk/__init__.py
neverbounce_sdk/account.py
neverbounce_sdk/auth.py
neverbounce_sdk/bulk.py
neverbounce_sdk/core.py
neverbounce_sdk/exceptions.py
neverbounce_sdk/poe.py
neverbounce_sdk/single.py
neverbounce_sdk/utils.py
neverbounce_sdk-4.2.8.dist-info/LICENSE
neverbounce_sdk-4.2.8.dist-info/METADATA
neverbounce_sdk-4.2.8.dist-info/WHEEL
neverbounce_sdk-4.2.8.dist-info/top_level.txt
neverbounce_sdk-4.2.8.dist-info/RECORD
