Metadata-Version: 2.1
Name: neverbounce-sdk
Version: 4.2.8
Summary: Official Python SDK for the NeverBounce API
Home-page: https://github.com/NeverBounce/NeverBounceApi-Python
Author: NeverBounce Team
Author-email: support@neverbounce.com
License: MIT
Keywords: neverbounce,api,email,verification,cleaning
Platform: UNKNOWN
Classifier: Development Status :: 5 - Production/Stable
Classifier: Intended Audience :: Developers
Classifier: Topic :: Communications :: Email
Classifier: License :: OSI Approved :: MIT License
Classifier: Natural Language :: English
Classifier: Programming Language :: Python :: 2
Classifier: Programming Language :: Python :: 2.7
Classifier: Programming Language :: Python :: 3
Classifier: Programming Language :: Python :: 3.3
Classifier: Programming Language :: Python :: 3.4
Classifier: Programming Language :: Python :: 3.5
Classifier: Programming Language :: Python :: 3.6
Classifier: Programming Language :: Python :: 3.7
Requires-Dist: requests
